browsepy/__init__.py
browsepy/__main__.py
browsepy/__meta__.py
browsepy/appconfig.py
browsepy/compat.py
browsepy/exceptions.py
browsepy/file.py
browsepy/manager.py
browsepy/mimetype.py
browsepy/stream.py
browsepy/widget.py
browsepy/plugin/__init__.py
browsepy/plugin/player/__init__.py
browsepy/plugin/player/playable.py
browsepy/plugin/player/tests.py
browsepy/plugin/player/static/css/base.css
browsepy/plugin/player/static/css/browse.css
browsepy/plugin/player/static/css/jplayer.blue.monday.css
browsepy/plugin/player/static/css/jplayer.blue.monday.min.css
browsepy/plugin/player/static/image/jplayer.blue.monday.jpg
browsepy/plugin/player/static/image/jplayer.blue.monday.seeking.gif
browsepy/plugin/player/static/image/jplayer.blue.monday.video.play.png
browsepy/plugin/player/static/js/base.js
browsepy/plugin/player/static/js/jplayer.playlist.min.js
browsepy/plugin/player/static/js/jquery.jplayer.min.js
browsepy/plugin/player/static/js/jquery.jplayer.swf
browsepy/plugin/player/static/js/jquery.min.js
browsepy/plugin/player/templates/audio.player.html
browsepy/static/base.css
browsepy/static/browse.directory.body.js
browsepy/static/browse.directory.head.js
browsepy/static/giorgio.jpg
browsepy/static/fonts/demo.html
browsepy/static/fonts/icomoon.eot
browsepy/static/fonts/icomoon.svg
browsepy/static/fonts/icomoon.ttf
browsepy/static/fonts/icomoon.woff
browsepy/templates/400.html
browsepy/templates/404.html
browsepy/templates/base.html
browsepy/templates/browse.html
browsepy/templates/remove.html
browsepy/tests/__init__.py
browsepy/tests/runner.py
browsepy/tests/test_app.py
browsepy/tests/test_compat.py
browsepy/tests/test_extensions.py
browsepy/tests/test_file.py
browsepy/tests/test_main.py
browsepy/tests/test_module.py
browsepy/tests/test_plugins.py
browsepy/tests/test_transform.py
browsepy/tests/utils.py
browsepy/tests/deprecated/__init__.py
browsepy/tests/deprecated/test_plugins.py
browsepy/tests/deprecated/plugin/__init__.py
browsepy/tests/deprecated/plugin/player.py
my_browsepy-0.0.2.dist-info/LICENSE
my_browsepy-0.0.2.dist-info/METADATA
my_browsepy-0.0.2.dist-info/WHEEL
my_browsepy-0.0.2.dist-info/entry_points.txt
my_browsepy-0.0.2.dist-info/top_level.txt
my_browsepy-0.0.2.dist-info/RECORD
