Metadata-Version: 2.1
Name: my_browsepy
Version: 0.0.2
Summary: Simple web file browser
Home-page: https://github.com/ergoithz/browsepy
Download-URL: https://github.com/ergoithz/browsepy/archive/0.0.2.tar.gz
Author: Felipe A. Hernandez
Author-email: ergoithz@gmail.com
License: MIT
Keywords: web,file,browser
Platform: any
Classifier: Development Status :: 4 - Beta
Classifier: License :: OSI Approved :: MIT License
Classifier: Operating System :: OS Independent
Classifier: Programming Language :: Python
Classifier: Programming Language :: Python :: 3
License-File: LICENSE
Requires-Dist: flask
Requires-Dist: unicategories
Requires-Dist: scandir
Requires-Dist: backports.shutil-get-terminal-size
